fastdates/Fastdates.py
fastdates/__init__.py
fastdates-0.1.4.dist-info/LICENSE
fastdates-0.1.4.dist-info/WHEEL
fastdates-0.1.4.dist-info/METADATA
fastdates-0.1.4.dist-info/RECORD
