Metadata-Version: 2.1
Name: fastdates
Version: 0.1.4
Summary: get common dates, fast!
Author-email: Yu Zhou <yuzhounc@gmail.com>
Requires-Python: >=3.7
Classifier: License :: OSI Approved :: MIT License
Project-URL: Home, https://github.com/yuzhoux/fastdates
